_tempest.cpython-311-x86_64-linux-gnu.so
tempest/__init__.py
tempest_anonymous.libs/libcuda-4c8d21d9.so.570.172.08
tempest_anonymous.libs/libcudart-09529672.so.12.6.77
tempest_anonymous.libs/libcurand-12411c1e.so.10.3.7.77
tempest_anonymous.libs/libgomp-0e7565f6.so.1.0.0
tempest_anonymous.libs/libtbb-163ea319.so.2
tempest_anonymous-1.4.4.dist-info/METADATA
tempest_anonymous-1.4.4.dist-info/WHEEL
tempest_anonymous-1.4.4.dist-info/top_level.txt
tempest_anonymous-1.4.4.dist-info/RECORD
