Metadata-Version: 2.1
Name: tempest-anonymous
Version: 1.4.4
Summary: A library to sample temporal random walks from in-memory temporal graphs
Home-page: https://github.com/anonymousresearcher1701/tempest-anonymous
Author: Anonymous Researcher1701
Author-email: anonymous.researcher1701@gmail.com
License: UNKNOWN
Platform: UNKNOWN
Requires-Python: >=3.8
Requires-Dist: pybind11>=2.6.0
Requires-Dist: numpy
Requires-Dist: networkx
